<?xml version="1.0" encoding="UTF-8"?>
<soapenv:Envelope xmlns:soapenv="http://schemas.xmlsoap.org/soap/envelope/" xmlns:urn="urn:riv:crm:carelisting:GetListingResponder:1" xmlns:urn1="urn:riv:crm:carelisting:1">
   <soapenv:Header/>
   <soapenv:Body>
      <urn:getListingResponse>
         <urn:subjectOfCare>
            <urn1:personId>121212-1212</urn1:personId>
            <urn1:listing>
               <urn1:validFromDate/>
               <urn1:validToDate/>
               <urn1:isInQueue>false</urn1:isInQueue>
               <urn1:listingType>BVC</urn1:listingType>
               <urn1:healthcare_facility>
                  <urn1:facilityId>SE90KC2-232A</urn1:facilityId>
                  <urn1:name>Björkhagens BVC</urn1:name>
                  <urn1:hasQueue>false</urn1:hasQueue>
               </urn1:healthcare_facility>
            </urn1:listing>
         </urn:subjectOfCare>
      </urn:getListingResponse>
   </soapenv:Body>
</soapenv:Envelope>